LICENSE.txt
polodb/__init__.py
polodb/core.py
polodb/version.py
polodb_python-0.1.18.dist-info/METADATA
polodb_python-0.1.18.dist-info/WHEEL
polodb_python-0.1.18.dist-info/licenses/LICENSE.txt
rust_polodb/__init__.py
rust_polodb/rust_polodb.cp39-win_amd64.pyd
polodb_python-0.1.18.dist-info/RECORD
