Metadata-Version: 2.4
Name: polodb-python
Version: 0.1.18
Classifier: Programming Language :: Rust
Classifier: Programming Language :: Python :: Implementation :: CPython
Classifier: Programming Language :: Python :: Implementation :: PyPy
Requires-Dist: importlib-metadata>=8.7.0
Requires-Dist: tomli>=2.2.1
License-File: LICENSE.txt
Summary: Add your description here
Home-Page: https://github.com/PoloDB/polodb-python
Author-email: SENHAJI RHAZI Hamza <hamza.senhajirhazi@gmail.com>
License: Apache License
Requires-Python: >=3.9
Project-URL: Source Code, https://github.com/PoloDB/polodb-python
